Workbook

Sheet Start Here
A1: Sideline Ready - Big-Ticket Amazon Products
A2: 959 products found on Amazon on Oct 30, 2026 from 154 sports-mom searches (2 pages each, Amazon's $100+ price filter).
A4: Rules every product passed
A5: Price $100 or more | 4.0 stars or higher | 100+ customer reviews | not a sponsored ad
A6: Off-topic results were removed (home space heaters, men's work boots, bed blankets, etc.), and for very crowded searches
A7: (weighted vests, dumbbells, massage guns, air tracks) only the top 10-12 by sales and reviews were kept.
A9: Tabs
A10: All Products: every product, sorted by category, then sport, then sales.
A11: Best Bets: the 302 products that also show 100+ bought last month AND 4.5+ stars. Start your bundles here.
A12: Summary: live counts by category, sport and price tier.
A14: Good to know
A15: 'Bought last month' is Amazon's own badge. A dash means Amazon didn't show one (usually under 50 sales that month).
... A18: Links use your tracking ID screenfreet0f-20.

Sheet All Products
A1: # | B1: Product | C1: Price (Oct 30) | D1: Stars | E1: Reviews | F1: Bought last month | G1: Price tier | H1: Category | I1: Sport | J1: Pinterest board | K1: Found by searching | L1: Already in 365 plan | M1: ASIN | N1: Affiliate link
A2: 1 | B2: Ninja Professional Plus Blender | C2: 109.99 | D2: 4.7 | E2: 19700 | F2: 10K+ | G2: $100-249 | H2: Athlete meals (blenders) | I2: All sports | J2: Teen Athlete Meals, Snacks & Meal Prep | K2: blender | M2: B0855B5Z6F | N2: https://www.amazon.com/dp/B0855B5Z6F?tag=screenfreet0f-20
A3: 2 | B3: nutribullet Pro+ Personal Blender | C3: 112.5 | D3: 4.5 | E3: 11900 | F3: 10K+ | G3: $100-249 | H3: Athlete meals (blenders) | I3: All sports | J3: Teen Athlete Meals, Snacks & Meal Prep | K3: blender | M3: B0BS76NRG3 | N3: https://www.amazon.com/dp/B0BS76NRG3?tag=screenfreet0f-20
A4: 3 | B4: Ninja Professional Blender 2.0 | C4: 109.99 | D4: 4.7 | E4: 48300 | F4: 8K+ | G4: $100-249 | H4: Athlete meals (blenders) | I4: All sports | J4: Teen Athlete Meals, Snacks & Meal Prep | K4: blender | M4: B0CKTYP1JT | N4: https://www.amazon.com/dp/B0CKTYP1JT?tag=screenfreet0f-20
A5: 4 | B5: Vitamix Propel Series 750 Blender | C5: 489 | D5: 4.4 | E5: 926 | F5: 2K+ | G5: $250-499 | H5: Athlete meals (blenders) | I5: All sports | J5: Teen Athlete Meals, Snacks & Meal Prep | K5: blender | M5: B0BWSJVTCJ | N5: https://www.amazon.com/dp/B0BWSJVTCJ?tag=screenfreet0f-20
A6: 5 | B6: Ninja Foodi TWISTi Blender DUO | C6: 119.94 | D6: 4.5 | E6: 4600 | F6: 1K+ | G6: $100-249 | H6: Athlete meals (blenders) | I6: All sports | J6: Teen Athlete Meals, Snacks & Meal Prep | K6: blender | M6: B09SBRGSFH | N6: https://www.amazon.com/dp/B09SBRGSFH?tag=screenfreet0f-20
A7: 6 | B7: CAP Rubber Coated Dumbbell Set with Rack | C7: 189.99 | D7: 4.4 | E7: 11800 | F7: 5K+ | G7: $100-249 | H7: Backyard & home training | I7: All sports | J7: Backyard Sports Training Equipment | K7: adjustable dumbbells | M7: B09NLF2J4P | N7: https://www.amazon.com/dp/B09NLF2J4P?tag=screenfreet0f-20
A8: 7 | B8: BowFlex SelectTech 840 Adjustable Kettlebell | C8: 149 | D8: 4.8 | E8: 7700 | F8: 3K+ | G8: $100-249 | H8: Backyard & home training | I8: All sports | J8: Backyard Sports Training Equipment | K8: adjustable dumbbells | M8: B07X64MXBS | N8: https://www.amazon.com/dp/B07X64MXBS?tag=screenfreet0f-20
A9: 8 | B9: BowFlex SelectTech Adjustable Dumbbells | C9: 399.99 | D9: 4.8 | E9: 334 | F9: 3K+ | G9: $250-499 | H9: Backyard & home training | I9: All sports | J9: Backyard Sports Training Equipment | K9: adjustable dumbbells | L9: Yes | M9: B0FRNG2N5H | N9: https://www.amazon.com/dp/B0FRNG2N5H?tag=screenfreet0f-20
A10: 9 | B10: PowerBlock Elite EXP 90 Adjustable Dumbbells | C10: 399 | D10: 4.6 | E10: 2600 | F10: 1K+ | G10: $250-499 | H10: Backyard & home training | I10: All sports | J10: Backyard Sports Training Equipment | K10: adjustable dumbbells | M10: B00A21NRNO | N10: https://www.amazon.com/dp/B00A21NRNO?tag=screenfreet0f-20
A11: 10 | B11: NordicTrack 55 lb Select-a-Weight Dumbbells | C11: 399 | D11: 4.5 | E11: 1900 | F11: 1K+ | G11: $250-499 | H11: Backyard & home training | I11: All sports | J11: Backyard Sports Training Equipment | K11: adjustable dumbbells | M11: B08BDD6GPC | N11: https://www.amazon.com/dp/B08BDD6GPC?tag=screenfreet0f-20
A12: 11 | B12: FDB2 Adjustable Dumbbell Set of 2 | C12: 139.99 | D12: 4.8 | E12: 635 | F12: 1K+ | G12: $100-249 | H12: Backyard & home training | I12: All sports | J12: Backyard Sports Training Equipment | K12: adjustable dumbbells | L12: Yes | M12: B0DK3H169C | N12: https://www.amazon.com/dp/B0DK3H169C?tag=screenfreet0f-20
A13: 12 | B13: Adjustable Dumbbell Set Pair 25/50 lb | C13: 239.99 | D13: 4.5 | E13: 164 | F13: 1K+ | G13: $100-249 | H13: Backyard & home training | I13: All sports | J13: Backyard Sports Training Equipment | K13: adjustable dumbbells | M13: B0GJ4HT8SS | N13: https://www.amazon.com/dp/B0GJ4HT8SS?tag=screenfreet0f-20
A14: 13 | B14: Lifepro Adjustable Dumbbells | C14: 189.99 | D14: 4.6 | E14: 3300 | F14: 900+ | G14: $100-249 | H14: Backyard & home training | I14: All sports | J14: Backyard Sports Training Equipment | K14: adjustable dumbbells | M14: B08QTGV9BW | N14: https://www.amazon.com/dp/B08QTGV9BW?tag=screenfreet0f-20
A15: 14 | B15: ERIC FLAG 40 lb Adjustable Weighted Vest | C15: 159.99 | D15: 4.7 | E15: 1100 | F15: 800+ | G15: $100-249 | H15: Backyard & home training | I15: All sports | J15: Backyard Sports Training Equipment | K15: weighted vest | M15: B09WB1BF81 | N15: https://www.amazon.com/dp/B09WB1BF81?tag=screenfreet0f-20
A16: 15 | B16: Adjustable Running Weighted Vest | C16: 119.99 | D16: 4.4 | E16: 489 | F16: 800+ | G16: $100-249 | H16: Backyard & home training | I16: All sports | J16: Backyard Sports Training Equipment | K16: weighted vest | M16: B0CZPRXQ3F | N16: https://www.amazon.com/dp/B0CZPRXQ3F?tag=screenfreet0f-20
A17: 16 | B17: Core Fitness Adjustable Dumbbell Set | C17: 369.99 | D17: 4.5 | E17: 1600 | F17: 700+ | G17: $250-499 | H17: Backyard & home training | I17: All sports | J17: Backyard Sports Training Equipment | K17: adjustable dumbbells | M17: B01J8S38LW | N17: https://www.amazon.com/dp/B01J8S38LW?tag=screenfreet0f-20
A18: 17 | B18: Adjustable Dumbbell Set 25/50 lb 10-in-1 | C18: 148.19 | D18: 4.5 | E18: 171 | F18: 700+ | G18: $100-249 | H18: Backyard & home training | I18: All sports | J18: Backyard Sports Training Equipment | K18: adjustable dumbbells | M18: B0FYNZQVB9 | N18: https://www.amazon.com/dp/B0FYNZQVB9?tag=screenfreet0f-20
A19: 18 | B19: CAP Power Rack Stand with Pull-Up Bar | C19: 119.99 | D19: 4.5 | E19: 4500 | F19: 600+ | G19: $100-249 | H19: Backyard & home training | I19: All sports | J19: Backyard Sports Training Equipment | K19: squat rack | M19: B00HYQP72O | N19: https://www.amazon.com/dp/B00HYQP72O?tag=screenfreet0f-20
A20: 19 | B20: Adjustable Dumbbell Set 20-90 lb | C20: 159.99 | D20: 4.3 | E20: 1400 | F20: 500+ | G20: $100-249 | H20: Backyard & home training | I20: All sports | J20: Backyard Sports Training Equipment | K20: adjustable dumbbells | M20: B0H4QWF2NK | N20: https://www.amazon.com/dp/B0H4QWF2NK?tag=screenfreet0f-20
A21: 20 | B21: Adjustable Dumbbell Set 20-90 lb 5-in-1 | C21: 159.99 | D21: 4.4 | E21: 2200 | F21: 400+ | G21: $100-249 | H21: Backyard & home training | I21: All sports | J21: Backyard Sports Training Equipment | K21: adjustable dumbbells | M21: B0HFVTQ8W8 | N21: https://www.amazon.com/dp/B0HFVTQ8W8?tag=screenfreet0f-20
A22: 21 | B22: Wolf Tactical Adjustable Weighted Vest | C22: 125.99 | D22: 4.6 | E22: 1600 | F22: 400+ | G22: $100-249 | H22: Backyard & home training | I22: All sports | J22: Backyard Sports Training Equipment | K22: weighted vest | M22: B08BX6SDJF | N22: https://www.amazon.com/dp/B08BX6SDJF?tag=screenfreet0f-20
A23: 22 | B23: Multi-Function Power Cage with J-Hooks | C23: 299.98 | D23: 4.6 | E23: 1100 | F23: 400+ | G23: $250-499 | H23: Backyard & home training | I23: All sports | J23: Backyard Sports Training Equipment | K23: squat rack | M23: B0BFQVVFB7 | N23: https://www.amazon.com/dp/B0BFQVVFB7?tag=screenfreet0f-20
A24: 23 | B24: SPORTSROYALS Power Rack | C24: 309.99 | D24: 4.5 | E24: 720 | F24: 300+ | G24: $250-499 | H24: Backyard & home training | I24: All sports | J24: Backyard Sports Training Equipment | K24: squat rack | M24: B0CXDZX29M | N24: https://www.amazon.com/dp/B0CXDZX29M?tag=screenfreet0f-20
... A66: 65 | B66: NWS Forza Spring-Loaded Agility Poles | C66: 112.99 | D66: 4.6 | E66: 126 | F66: - | G66: $100-249 | H66: Backyard & home training | I66: All sports | J66: Backyard Sports Training Equipment | K66: agility training | M66: B077PQ5MS5 | N66: https://www.amazon.com/dp/B077PQ5MS5?tag=screenfreet0f-20
A67: 66 | B67: Bushnell Velocity Radar Speed Gun | C67: 149.96 | D67: 4.3 | E67: 4600 | F67: 800+ | G67: $100-249 | H67: Backyard & home training | I67: Baseball | J67: Backyard Sports Training Equipment | K67: radar gun baseball | L67: Yes | M67: B0002X7V1Q | N67: https://www.amazon.com/dp/B0002X7V1Q?tag=screenfreet0f-20
A68: 67 | B68: Pocket Radar Smart Coach with Sports App | C68: 399 | D68: 4.6 | E68: 1400 | F68: 500+ | G68: $250-499 | H68: Backyard & home training | I68: Baseball | J68: Backyard Sports Training Equipment | K68: radar gun baseball | L68: Yes | M68: B07H7SN831 | N68: https://www.amazon.com/dp/B07H7SN831?tag=screenfreet0f-20
A69: 68 | B69: Louisville Slugger Blue Flame Pitching Machine | C69: 139 | D69: 4.5 | E69: 3600 | F69: 300+ | G69: $100-249 | H69: Backyard & home training | I69: Baseball | J69: Backyard Sports Training Equipment | K69: pitching machine | L69: Yes | M69: B000VZ2Q5G | N69: https://www.amazon.com/dp/B000VZ2Q5G?tag=screenfreet0f-20
A70: 69 | B70: Tanner Heavy Batting Tee | C70: 129.99 | D70: 4.9 | E70: 1100 | F70: 300+ | G70: $100-249 | H70: Backyard & home training | I70: Baseball | J70: Backyard Sports Training Equipment | K70: batting tee | L70: Yes | M70: B01D8ZLL2O | N70: https://www.amazon.com/dp/B01D8ZLL2O?tag=screenfreet0f-20
A71: 70 | B71: Pocket Radar Ball Coach | C71: 299 | D71: 4.6 | E71: 931 | F71: 200+ | G71: $250-499 | H71: Backyard & home training | I71: Baseball | J71: Backyard Sports Training Equipment | K71: radar gun baseball | M71: B00ISCXPJA | N71: https://www.amazon.com/dp/B00ISCXPJA?tag=screenfreet0f-20
A72: 71 | B72: Louisville Slugger Black Flame Pitching Machine | C72: 215.79 | D72: 4.5 | E72: 1400 | F72: 100+ | G72: $100-249 | H72: Backyard & home training | I72: Baseball | J72: Backyard Sports Training Equipment | K72: pitching machine | L72: Yes | M72: B00GOEZRQS | N72: https://www.amazon.com/dp/B00GOEZRQS?tag=screenfreet0f-20
A73: 72 | B73: Rope Bat Original Swing Trainer w/ 12 Balls | C73: 138.95 | D73: 4.6 | E73: 1200 | F73: 100+ | G73: $100-249 | H73: Backyard & home training | I73: Baseball | J73: Backyard Sports Training Equipment | K73: baseball rebounder | M73: B01LXO616B | N73: https://www.amazon.com/dp/B01LXO616B?tag=screenfreet0f-20
A74: 73 | B74: Heater Sports Slider Lite 360 Baseball Pitching Machine | C74: 179.99 | D74: 4.1 | E74: 529 | F74: 100+ | G74: $100-249 | H74: Backyard & home training | I74: Baseball | J74: Backyard Sports Training Equipment | K74: pitching machine | M74: B00169186O | N74: https://www.amazon.com/dp/B00169186O?tag=screenfreet0f-20
A75: 74 | B75: Athlon Rangecraft Velocity Pro Radar | C75: 399.99 | D75: 4.7 | E75: 343 | F75: 100+ | G75: $250-499 | H75: Backyard & home training | I75: Baseball | J75: Backyard Sports Training Equipment | K75: radar gun baseball | M75: B0DZQYB35H | N75: https://www.amazon.com/dp/B0DZQYB35H?tag=screenfreet0f-20
A76: 75 | B76: Lacrosse Rebounder with 5 Adjustable Angles | C76: 109.99 | D76: 4.6 | E76: 263 | F76: 100+ | G76: $100-249 | H76: Backyard & home training | I76: Baseball | J76: Backyard Sports Training Equipment | K76: baseball rebounder | M76: B0DCYRM1C7 | N76: https://www.amazon.com/dp/B0DCYRM1C7?tag=screenfreet0f-20
A77: 76 | B77: Skywalker Sports Baseball & Softball Safety Screen | C77: 109.99 | D77: 4.8 | E77: 253 | F77: 100+ | G77: $100-249 | H77: Backyard & home training | I77: Baseball | J77: Backyard Sports Training Equipment | K77: baseball hitting net | M77: B07Q34XHLL | N77: https://www.amazon.com/dp/B07Q34XHLL?tag=screenfreet0f-20
A78: 77 | B78: Portable Batting Cage 22x12x8 ft with Pitching Net | C78: 149.95 | D78: 4 | E78: 203 | F78: 100+ | G78: $100-249 | H78: Backyard & home training | I78: Baseball | J78: Backyard Sports Training Equipment | K78: pitching machine | M78: B0D6X1XTQP | N78: https://www.amazon.com/dp/B0D6X1XTQP?tag=screenfreet0f-20
A79: 78 | B79: VEVOR Multi-Sport Backstop Barricade Net | C79: 105.9 | D79: 4.4 | E79: 181 | F79: 100+ | G79: $100-249 | H79: Backyard & home training | I79: Baseball | J79: Backyard Sports Training Equipment | K79: baseball hitting net | M79: B0DDT3TCBJ | N79: https://www.amazon.com/dp/B0DDT3TCBJ?tag=screenfreet0f-20
A80: 79 | B80: Heavy-Duty Pro 9 Hole Pitching Net with Strike Zone | C80: 113.98 | D80: 4.5 | E80: 125 | F80: 100+ | G80: $100-249 | H80: Backyard & home training | I80: Baseball | J80: Backyard Sports Training Equipment | K80: pitching net | L80: Yes | M80: B0DRYKTLJ6 | N80: https://www.amazon.com/dp/B0DRYKTLJ6?tag=screenfreet0f-20
A81: 80 | B81: GoSports Hitting Mat with Batting Stance Alignment | C81: 129.99 | D81: 4.6 | E81: 122 | F81: 100+ | G81: $100-249 | H81: Backyard & home training | I81: Baseball | J81: Backyard Sports Training Equipment | K81: baseball training aid | M81: B0CVJQQXJS | N81: https://www.amazon.com/dp/B0CVJQQXJS?tag=screenfreet0f-20
A82: 81 | B82: Baseball Tee with LED Light and Adjustable Height | C82: 129.99 | D82: 4.5 | E82: 111 | F82: 100+ | G82: $100-249 | H82: Backyard & home training | I82: Baseball | J82: Backyard Sports Training Equipment | K82: batting tee | M82: B08DKZWPWZ | N82: https://www.amazon.com/dp/B08DKZWPWZ?tag=screenfreet0f-20
A83: 82 | B83: PowerNet Baseball Softball Practice Net 7x7 with Accessories | C83: 139.99 | D83: 4.8 | E83: 14800 | F83: 50+ | G83: $100-249 | H83: Backyard & home training | I83: Baseball | J83: Backyard Sports Training Equipment | K83: baseball hitting net | M83: B017OAE9MS | N83: https://www.amazon.com/dp/B017OAE9MS?tag=screenfreet0f-20
A84: 83 | B84: SKLZ Hit-A-Way Youth Baseball Swing Trainer | C84: 199.99 | D84: 4.4 | E84: 2600 | F84: 50+ | G84: $100-249 | H84: Backyard & home training | I84: Baseball | J84: Backyard Sports Training Equipment | K84: baseball rebounder | M84: B002MADLCA | N84: https://www.amazon.com/dp/B002MADLCA?tag=screenfreet0f-20
A85: 84 | B85: Jugs T Pro Style Batting Tee | C85: 104.99 | D85: 4.9 | E85: 1800 | F85: 50+ | G85: $100-249 | H85: Backyard & home training | I85: Baseball | J85: Backyard Sports Training Equipment | K85: batting tee | M85: B018R6OMJ8 | N85: https://www.amazon.com/dp/B018R6OMJ8?tag=screenfreet0f-20
A86: 85 | B86: Pocket Radar Ball Coach Bundle with Mount | C86: 299.95 | D86: 4.6 | E86: 867 | F86: 50+ | G86: $250-499 | H86: Backyard & home training | I86: Baseball | J86: Backyard Sports Training Equipment | K86: radar gun baseball | M86: B00KGHXUZ4 | N86: https://www.amazon.com/dp/B00KGHXUZ4?tag=screenfreet0f-20
A87: 86 | B87: ZELUS Multi-Sport Backstop Net | C87: 113.99 | D87: 4.1 | E87: 490 | F87: 50+ | G87: $100-249 | H87: Backyard & home training | I87: Baseball | J87: Backyard Sports Training Equipment | K87: pitching net | M87: B0CPPVZKKV | N87: https://www.amazon.com/dp/B0CPPVZKKV?tag=screenfreet0f-20
A88: 87 | B88: QuickPlay Tekkers Trainer Soccer Rebounder | C88: 109.99 | D88: 4.6 | E88: 421 | F88: 50+ | G88: $100-249 | H88: Backyard & home training | I88: Baseball | J88: Backyard Sports Training Equipment | K88: baseball rebounder | M88: B09KMLYLWL | N88: https://www.amazon.com/dp/B09KMLYLWL?tag=screenfreet0f-20
A89: 88 | B89: LoFli Reduced-Flight Practice Baseballs | C89: 119.99 | D89: 4.7 | E89: 260 | F89: 50+ | G89: $100-249 | H89: Backyard & home training | I89: Baseball | J89: Backyard Sports Training Equipment | K89: baseball training aid | M89: B0GXGW8K1N | N89: https://www.amazon.com/dp/B0GXGW8K1N?tag=screenfreet0f-20
A90: 89 | B90: PowerNet Launch F-lite Softball & Baseball Pitching Machine | C90: 409.99 | D90: 4.2 | E90: 248 | F90: 50+ | G90: $250-499 | H90: Backyard & home training | I90: Baseball | J90: Backyard Sports Training Equipment | K90: pitching machine | M90: B08S21KMYM | N90: https://www.amazon.com/dp/B08S21KMYM?tag=screenfreet0f-20
A91: 90 | B91: Franklin Sports Basketball Pass Back Rebounder | C91: 130.49 | D91: 4.1 | E91: 229 | F91: 50+ | G91: $100-249 | H91: Backyard & home training | I91: Baseball | J91: Backyard Sports Training Equipment | K91: baseball rebounder | M91: B09J1LRBHY | N91: https://www.amazon.com/dp/B09J1LRBHY?tag=screenfreet0f-20
A92: 91 | B92: Baseball Rebounder Net 4x4.5 ft with Strike Zones | C92: 139.99 | D92: 4.3 | E92: 197 | F92: 50+ | G92: $100-249 | H92: Backyard & home training | I92: Baseball | J92: Backyard Sports Training Equipment | K92: baseball rebounder | M92: B0DC6V7JZR | N92: https://www.amazon.com/dp/B0DC6V7JZR?tag=screenfreet0f-20
... A132: 131 | B132: MR Professional Baseball Pitching Screen | C132: 103.99 | D132: 4.2 | E132: 102 | F132: - | G132: $100-249 | H132: Backyard & home training | I132: Baseball | J132: Backyard Sports Training Equipment | K132: baseball hitting net | M132: B09SX1KX4W | N132: https://www.amazon.com/dp/B09SX1KX4W?tag=screenfreet0f-20
A133: 132 | B133: Portable Basketball Hoop 5.6-10 ft Adjustable | C133: 159.99 | D133: 4.5 | E133: 1200 | F133: 1K+ | G133: $100-249 | H133: Backyard & home training | I133: Basketball | J133: Backyard Sports Training Equipment | K133: basketball hoop portable | L133: Yes | M133: B0GJRYPQ3D | N133: https://www.amazon.com/dp/B0GJRYPQ3D?tag=screenfreet0f-20
A134: 133 | B134: Pop-A-Shot Official Dual Shot Sport Arcade Basketball | C134: 229.99 | D134: 4.6 | E134: 3300 | F134: 500+ | G134: $100-249 | H134: Backyard & home training | I134: Basketball | J134: Backyard Sports Training Equipment | K134: basketball hoop portable | L134: Yes | M134: B0BHLHBGJ9 | N134: https://www.amazon.com/dp/B0BHLHBGJ9?tag=screenfreet0f-20
A135: 134 | B135: XbotGo Chameleon AI Auto-Tracking Sports Camera | C135: 254.99 | D135: 4.1 | E135: 794 | F135: 300+ | G135: $250-499 | H135: Backyard & home training | I135: Basketball | J135: Backyard Sports Training Equipment | K135: basketball shooting machine | M135: B0DG2DYQD8 | N135: https://www.amazon.com/dp/B0DG2DYQD8?tag=screenfreet0f-20
A136: 135 | B136: Basketball Hoop 40/44/48" Backboard 5.3-10 ft | C136: 179.99 | D136: 4.3 | E136: 605 | F136: 300+ | G136: $100-249 | H136: Backyard & home training | I136: Basketball | J136: Backyard Sports Training Equipment | K136: basketball hoop portable | M136: B0GGYZBZ7X | N136: https://www.amazon.com/dp/B0GGYZBZ7X?tag=screenfreet0f-20
A137: 136 | B137: Kids Basketball Hoop 4-8.5 ft Adjustable | C137: 169.99 | D137: 4.3 | E137: 194 | F137: 300+ | G137: $100-249 | H137: Backyard & home training | I137: Basketball | J137: Backyard Sports Training Equipment | K137: basketball hoop portable | M137: B0GDDTHW6X | N137: https://www.amazon.com/dp/B0GDDTHW6X?tag=screenfreet0f-20
A138: 137 | B138: Pop-A-Shot Dual Shot Sport Arcade Basketball | C138: 299.99 | D138: 4.6 | E138: 3300 | F138: 200+ | G138: $250-499 | H138: Backyard & home training | I138: Basketball | J138: Backyard Sports Training Equipment | K138: basketball shooting machine | M138: B07XFPSZ58 | N138: https://www.amazon.com/dp/B07XFPSZ58?tag=screenfreet0f-20
A139: 138 | B139: Yohood Outdoor Basketball Hoop 4.4-10 ft | C139: 118.08 | D139: 4.4 | E139: 1800 | F139: 200+ | G139: $100-249 | H139: Backyard & home training | I139: Basketball | J139: Backyard Sports Training Equipment | K139: basketball hoop portable | M139: B0C36CVLG1 | N139: https://www.amazon.com/dp/B0C36CVLG1?tag=screenfreet0f-20
A140: 139 | B140: Silverback NXT 54" Wall Mounted Basketball Hoop | C140: 439.95 | D140: 4.7 | E140: 1200 | F140: 200+ | G140: $250-499 | H140: Backyard & home training | I140: Basketball | J140: Backyard Sports Training Equipment | K140: basketball hoop portable | M140: B07F9VNSN6 | N140: https://www.amazon.com/dp/B07F9VNSN6?tag=screenfreet0f-20
A141: 140 | B141: Portable Basketball Hoop 44/47" 5.3-10 ft | C141: 179.99 | D141: 4.5 | E141: 298 | F141: 200+ | G141: $100-249 | H141: Backyard & home training | I141: Basketball | J141: Backyard Sports Training Equipment | K141: basketball hoop portable | M141: B0CTMTF4PD | N141: https://www.amazon.com/dp/B0CTMTF4PD?tag=screenfreet0f-20
A142: 141 | B142: Seray 40" Shatterproof Basketball Hoop 3.4-10 ft | C142: 169.99 | D142: 4.5 | E142: 185 | F142: 200+ | G142: $100-249 | H142: Backyard & home training | I142: Basketball | J142: Backyard Sports Training Equipment | K142: basketball hoop portable | M142: B0FH8ZJ84N | N142: https://www.amazon.com/dp/B0FH8ZJ84N?tag=screenfreet0f-20
A143: 142 | B143: Asbest Portable Adjustable Basketball Hoop 44/48" | C143: 179.99 | D143: 4.4 | E143: 128 | F143: 200+ | G143: $100-249 | H143: Backyard & home training | I143: Basketball | J143: Backyard Sports Training Equipment | K143: basketball hoop portable | M143: B0FMNK26T4 | N143: https://www.amazon.com/dp/B0FMNK26T4?tag=screenfreet0f-20
A144: 143 | B144: Spalding Momentous Portable Basketball Hoop | C144: 622.99 | D144: 4.5 | E144: 103 | F144: 200+ | G144: $500-999 | H144: Backyard & home training | I144: Basketball | J144: Backyard Sports Training Equipment | K144: basketball hoop portable | L144: Yes | M144: B0BYFBT9LK | N144: https://www.amazon.com/dp/B0BYFBT9LK?tag=screenfreet0f-20
A145: 144 | B145: Lifetime NBA League Edition Portable Basketball Hoop | C145: 269 | D145: 4.6 | E145: 5400 | F145: 100+ | G145: $250-499 | H145: Backyard & home training | I145: Basketball | J145: Backyard Sports Training Equipment | K145: basketball hoop portable | M145: B0FS8T1WQW | N145: https://www.amazon.com/dp/B0FS8T1WQW?tag=screenfreet0f-20
A146: 145 | B146: Pop-A-Shot Home Dual Shot Arcade Basketball | C146: 309.99 | D146: 4.6 | E146: 3500 | F146: 100+ | G146: $250-499 | H146: Backyard & home training | I146: Basketball | J146: Backyard Sports Training Equipment | K146: basketball shooting machine | M146: B0BJFLTJ4Q | N146: https://www.amazon.com/dp/B0BJFLTJ4Q?tag=screenfreet0f-20
A147: 146 | B147: Silverback In-Ground Basketball Hoop Tempered Glass | C147: 1199.95 | D147: 4.5 | E147: 1500 | F147: 100+ | G147: $1,000+ | H147: Backyard & home training | I147: Basketball | J147: Backyard Sports Training Equipment | K147: basketball hoop portable | L147: Yes | M147: B096T5DNS8 | N147: https://www.amazon.com/dp/B096T5DNS8?tag=screenfreet0f-20
A148: 147 | B148: Lifetime Portable 48" Basketball Hoop 8-10 ft | C148: 269 | D148: 4.4 | E148: 998 | F148: 100+ | G148: $250-499 | H148: Backyard & home training | I148: Basketball | J148: Backyard Sports Training Equipment | K148: basketball hoop portable | M148: B0013IQENU | N148: https://www.amazon.com/dp/B0013IQENU?tag=screenfreet0f-20
A149: 148 | B149: Yohood Portable 44/48" Basketball Hoop | C149: 199.99 | D149: 4.5 | E149: 712 | F149: 100+ | G149: $100-249 | H149: Backyard & home training | I149: Basketball | J149: Backyard Sports Training Equipment | K149: basketball hoop portable | M149: B0DBQJWP4Y | N149: https://www.amazon.com/dp/B0DBQJWP4Y?tag=screenfreet0f-20
A150: 149 | B150: Pop-A-Shot Indoor/Outdoor Dual Shot Arcade Basketball | C150: 339.99 | D150: 4.2 | E150: 583 | F150: 100+ | G150: $250-499 | H150: Backyard & home training | I150: Basketball | J150: Backyard Sports Training Equipment | K150: basketball shooting machine | M150: B07Z8BT3HM | N150: https://www.amazon.com/dp/B07Z8BT3HM?tag=screenfreet0f-20
A151: 150 | B151: Spalding TF DNA Smart Basketball (shot tracking) | C151: 249.99 | D151: 4.3 | E151: 515 | F151: 100+ | G151: $100-249 | H151: Backyard & home training | I151: Basketball | J151: Backyard Sports Training Equipment | K151: basketball hoop in ground | M151: B0BGQGTVYR | N151: https://www.amazon.com/dp/B0BGQGTVYR?tag=screenfreet0f-20
A152: 151 | B152: Yohood In-Ground Basketball Hoop 10 ft | C152: 279.99 | D152: 4.2 | E152: 388 | F152: 100+ | G152: $250-499 | H152: Backyard & home training | I152: Basketball | J152: Backyard Sports Training Equipment | K152: basketball hoop portable | M152: B0G1LDTG4S | N152: https://www.amazon.com/dp/B0G1LDTG4S?tag=screenfreet0f-20
A153: 152 | B153: Basketball Hoop 44/48/54" Shatterproof Backboard | C153: 189.99 | D153: 4.4 | E153: 340 | F153: 100+ | G153: $100-249 | H153: Backyard & home training | I153: Basketball | J153: Backyard Sports Training Equipment | K153: basketball hoop portable | M153: B0DZ278HW7 | N153: https://www.amazon.com/dp/B0DZ278HW7?tag=screenfreet0f-20
A154: 153 | B154: Asbest Portable Basketball Hoop 44" 5.6-10 ft | C154: 158.99 | D154: 4.5 | E154: 122 | F154: 100+ | G154: $100-249 | H154: Backyard & home training | I154: Basketball | J154: Backyard Sports Training Equipment | K154: basketball hoop portable | M154: B0FTTT7ZRY | N154: https://www.amazon.com/dp/B0FTTT7ZRY?tag=screenfreet0f-20
A155: 154 | B155: Backyard Blitz 44/47" Adjustable Basketball Hoop | C155: 299.99 | D155: 4.2 | E155: 104 | F155: 100+ | G155: $250-499 | H155: Backyard & home training | I155: Basketball | J155: Backyard Sports Training Equipment | K155: basketball hoop portable | M155: B0FS1JC6VF | N155: https://www.amazon.com/dp/B0FS1JC6VF?tag=screenfreet0f-20
A156: 155 | B156: Basketball Hoop 44/52" Shatterproof Backboard | C156: 239.99 | D156: 4.3 | E156: 100 | F156: 100+ | G156: $100-249 | H156: Backyard & home training | I156: Basketball | J156: Backyard Sports Training Equipment | K156: basketball hoop portable | M156: B0FQV1MC4V | N156: https://www.amazon.com/dp/B0FQV1MC4V?tag=screenfreet0f-20
A157: 156 | B157: Lifetime Portable 44" Basketball Hoop 7.5-10 ft | C157: 209.22 | D157: 4.6 | E157: 5400 | F157: 50+ | G157: $100-249 | H157: Backyard & home training | I157: Basketball | J157: Backyard Sports Training Equipment | K157: basketball hoop portable | M157: B0015S9FPW | N157: https://www.amazon.com/dp/B0015S9FPW?tag=screenfreet0f-20
A158: 157 | B158: Foldable Indoor Double Shot Basketball Arcade Game | C158: 109.99 | D158: 4.4 | E158: 1400 | F158: 50+ | G158: $100-249 | H158: Backyard & home training | I158: Basketball | J158: Backyard Sports Training Equipment | K158: basketball shooting machine | M158: B07G18C432 | N158: https://www.amazon.com/dp/B07G18C432?tag=screenfreet0f-20
A159: 158 | B159: Giantex Folding Dual Shot Basketball Arcade Game | C159: 129.99 | D159: 4.4 | E159: 1100 | F159: 50+ | G159: $100-249 | H159: Backyard & home training | I159: Basketball | J159: Backyard Sports Training Equipment | K159: basketball shooting machine | M159: B0CPSF8MPG | N159: https://www.amazon.com/dp/B0CPSF8MPG?tag=screenfreet0f-20
... A204: 203 | B204: Foldable Electronic Dual Basketball Arcade Game | C204: 139.99 | D204: 4.3 | E204: 119 | F204: - | G204: $100-249 | H204: Backyard & home training | I204: Basketball | J204: Backyard Sports Training Equipment | K204: basketball shooting machine | M204: B0BFGQGM32 | N204: https://www.amazon.com/dp/B0BFGQGM32?tag=screenfreet0f-20
A205: 204 | B205: GoSports Heavy Duty Football Tackling Dummy | C205: 139.99 | D205: 4.7 | E205: 798 | F205: 100+ | G205: $100-249 | H205: Backyard & home training | I205: Football | J205: Backyard Sports Training Equipment | K205: football tackling dummy | L205: Yes | M205: B07T86B5WL | N205: https://www.amazon.com/dp/B07T86B5WL?tag=screenfreet0f-20
A206: 205 | B206: Goalrilla Tackling Dummy with Heavy-Duty Handles | C206: 159.99 | D206: 4.7 | E206: 938 | F206: - | G206: $100-249 | H206: Backyard & home training | I206: Football | J206: Backyard Sports Training Equipment | K206: football tackling dummy | M206: B005G1N7VC | N206: https://www.amazon.com/dp/B005G1N7VC?tag=screenfreet0f-20
A207: 206 | B207: Aoneky Heavy Duty Soccer Backstop Net | C207: 114.99 | D207: 4.5 | E207: 350 | F207: - | G207: $100-249 | H207: Backyard & home training | I207: Football | J207: Backyard Sports Training Equipment | K207: football kicking net | M207: B07Z34P2HK | N207: https://www.amazon.com/dp/B07Z34P2HK?tag=screenfreet0f-20
A208: 207 | B208: SKLZ Quickster Football Kicking Net | C208: 233.5 | D208: 4.3 | E208: 330 | F208: - | G208: $100-249 | H208: Backyard & home training | I208: Football | J208: Backyard Sports Training Equipment | K208: football tackling dummy | M208: B00CMSXIJI | N208: https://www.amazon.com/dp/B00CMSXIJI?tag=screenfreet0f-20
A209: 208 | B209: Kwik Goal All-Surface Soccer Tennis Net | C209: 124.95 | D209: 4.5 | E209: 213 | F209: - | G209: $100-249 | H209: Backyard & home training | I209: Football | J209: Backyard Sports Training Equipment | K209: football kicking net | M209: B0026OK9PY | N209: https://www.amazon.com/dp/B0026OK9PY?tag=screenfreet0f-20
A210: 209 | B210: Football Stand-Up Blocking Dummy | C210: 105.52 | D210: 4.7 | E210: 199 | F210: - | G210: $100-249 | H210: Backyard & home training | I210: Football | J210: Backyard Sports Training Equipment | K210: football tackling dummy | M210: B0C7RQKXP8 | N210: https://www.amazon.com/dp/B0C7RQKXP8?tag=screenfreet0f-20
A211: 210 | B211: Football Tackle Dummy with Water-Weighted Base | C211: 135.18 | D211: 4.3 | E211: 166 | F211: - | G211: $100-249 | H211: Backyard & home training | I211: Football | J211: Backyard Sports Training Equipment | K211: football tackling dummy | M211: B091WZ29CP | N211: https://www.amazon.com/dp/B091WZ29CP?tag=screenfreet0f-20
A212: 211 | B212: Murray Sporting Goods Heavy Duty Tackling Dummy | C212: 119.99 | D212: 4.3 | E212: 100 | F212: - | G212: $100-249 | H212: Backyard & home training | I212: Football | J212: Backyard Sports Training Equipment | K212: football tackling dummy | M212: B0BZDTY2MC | N212: https://www.amazon.com/dp/B0BZDTY2MC?tag=screenfreet0f-20
A213: 212 | B213: Bushnell Tour V6 Shift Laser Rangefinder | C213: 299.99 | D213: 4.7 | E213: 638 | F213: 1K+ | G213: $250-499 | H213: Backyard & home training | I213: Golf | J213: Backyard Sports Training Equipment | K213: golf launch monitor | M213: B0C4TNKZFG | N213: https://www.amazon.com/dp/B0C4TNKZFG?tag=screenfreet0f-20
A214: 213 | B214: Rapsodo Mobile Launch Monitor | C214: 129.98 | D214: 4.1 | E214: 3100 | F214: 500+ | G214: $100-249 | H214: Backyard & home training | I214: Golf | J214: Backyard Sports Training Equipment | K214: golf launch monitor | M214: B07T91KFMP | N214: https://www.amazon.com/dp/B07T91KFMP?tag=screenfreet0f-20
A215: 214 | B215: Perfect Practice Putting Mat & Chipping Net | C215: 149.99 | D215: 4.6 | E215: 1700 | F215: 400+ | G215: $100-249 | H215: Backyard & home training | I215: Golf | J215: Backyard Sports Training Equipment | K215: golf hitting mat | M215: B07YQ7935B | N215: https://www.amazon.com/dp/B07YQ7935B?tag=screenfreet0f-20
A216: 215 | B216: Garmin Approach R10 Portable Launch Monitor | C216: 499.99 | D216: 4.1 | E216: 1100 | F216: 300+ | G216: $250-499 | H216: Backyard & home training | I216: Golf | J216: Backyard Sports Training Equipment | K216: golf launch monitor | M216: B095QX1FSR | N216: https://www.amazon.com/dp/B095QX1FSR?tag=screenfreet0f-20
A217: 216 | B217: Voice Caddie Portable Launch Monitor | C217: 234.99 | D217: 4.2 | E217: 737 | F217: 200+ | G217: $100-249 | H217: Backyard & home training | I217: Golf | J217: Backyard Sports Training Equipment | K217: golf launch monitor | M217: B07R8JV36B | N217: https://www.amazon.com/dp/B07R8JV36B?tag=screenfreet0f-20
... A219: 218 | B219: RELIFE Free-Standing Pull-Up Bar Power Tower | C219: 129.99 | D219: 4.4 | E219: 8400 | F219: 900+ | G219: $100-249 | H219: Backyard & home training | I219: Gymnastics | J219: Backyard Sports Training Equipment | K219: gymnastics bar | M219: B071HT1DH1 | N219: https://www.amazon.com/dp/B071HT1DH1?tag=screenfreet0f-20
A220: 219 | B220: Adjustable Gymnastics Horizontal Bar for Kids | C220: 144.99 | D220: 4.6 | E220: 408 | F220: 500+ | G220: $100-249 | H220: Backyard & home training | I220: Gymnastics | J220: Backyard Sports Training Equipment | K220: gymnastics bar | L220: Yes | M220: B0CQWWWHSC | N220: https://www.amazon.com/dp/B0CQWWWHSC?tag=screenfreet0f-20
A221: 220 | B221: BalanceFrom 10x4 ft 4-Panel Folding Gymnastics Mat | C221: 109.99 | D221: 4.7 | E221: 12600 | F221: 400+ | G221: $100-249 | H221: Backyard & home training | I221: Gymnastics | J221: Backyard Sports Training Equipment | K221: gymnastics bar | M221: B0722VRW3V | N221: https://www.amazon.com/dp/B0722VRW3V?tag=screenfreet0f-20
A222: 221 | B222: FBSPORT Inflatable Air Track Tumbling Mat | C222: 119.99 | D222: 4.7 | E222: 3100 | F222: 400+ | G222: $100-249 | H222: Backyard & home training | I222: Gymnastics | J222: Backyard Sports Training Equipment | K222: air track | L222: Yes | M222: B078815CXR | N222: https://www.amazon.com/dp/B078815CXR?tag=screenfreet0f-20
A223: 222 | B223: AKSPORT Gymnastics Air Mat Tumble Track | C223: 125.99 | D223: 4.6 | E223: 3600 | F223: 200+ | G223: $100-249 | H223: Backyard & home training | I223: Gymnastics | J223: Backyard Sports Training Equipment | K223: gymnastics bar | M223: B07L8WW3QP | N223: https://www.amazon.com/dp/B07L8WW3QP?tag=screenfreet0f-20
A224: 223 | B224: AWSUM Inflatable Air Tumbling Mat with Pump | C224: 159.99 | D224: 4.6 | E224: 1900 | F224: 200+ | G224: $100-249 | H224: Backyard & home training | I224: Gymnastics | J224: Backyard Sports Training Equipment | K224: air track | M224: B0BHSQ7VPS | N224: https://www.amazon.com/dp/B0BHSQ7VPS?tag=screenfreet0f-20
A225: 224 | B225: Kangaroo Hoppers Gymnastics Cheese Wedge Mat | C225: 169.99 | D225: 4.7 | E225: 884 | F225: 200+ | G225: $100-249 | H225: Backyard & home training | I225: Gymnastics | J225: Backyard Sports Training Equipment | K225: gymnastics mat | M225: B0BRSKYBT7 | N225: https://www.amazon.com/dp/B0BRSKYBT7?tag=screenfreet0f-20
...

Sheet Best Bets
A1: # | B1: Product | C1: Price (Oct 30) | D1: Stars | E1: Reviews | F1: Bought last month | G1: Price tier | H1: Category | I1: Sport | J1: Pinterest board | K1: Found by searching | L1: Already in 365 plan | M1: ASIN | N1: Affiliate link
A2: 1 | B2: Beats Solo 4 Wireless Headphones | C2: 129.95 | D2: 4.6 | E2: 30000 | F2: 10K+ | G2: $100-249 | H2: Tech gifts | I2: All sports | J2: Sports Mom Gifts & Gift Baskets | K2: noise cancelling headphones | M2: B0CZPGX972 | N2: https://www.amazon.com/dp/B0CZPGX972?tag=screenfreet0f-20
A3: 2 | B3: Apple iPad 11-inch (A16) | C3: 399 | D3: 4.7 | E3: 29900 | F3: 10K+ | G3: $250-499 | H3: Tech gifts | I3: All sports | J3: Sports Mom Gifts & Gift Baskets | K3: ipad | M3: B0DZ77D5HL | N3: https://www.amazon.com/dp/B0DZ77D5HL?tag=screenfreet0f-20
A4: 3 | B4: Beats Studio Pro Wireless Headphones | C4: 199.95 | D4: 4.5 | E4: 29000 | F4: 10K+ | G4: $100-249 | H4: Tech gifts | I4: All sports | J4: Sports Mom Gifts & Gift Baskets | K4: noise cancelling headphones | M4: B0C8PR4W22 | N4: https://www.amazon.com/dp/B0C8PR4W22?tag=screenfreet0f-20
A5: 4 | B5: Bose QuietComfort Wireless Headphones | C5: 169 | D5: 4.5 | E5: 22500 | F5: 10K+ | G5: $100-249 | H5: Tech gifts | I5: All sports | J5: Sports Mom Gifts & Gift Baskets | K5: noise cancelling headphones | M5: B0DZHR44J9 | N5: https://www.amazon.com/dp/B0DZHR44J9?tag=screenfreet0f-20
A6: 5 | B6: Ninja Professional Plus Blender | C6: 109.99 | D6: 4.7 | E6: 19700 | F6: 10K+ | G6: $100-249 | H6: Athlete meals (blenders) | I6: All sports | J6: Teen Athlete Meals, Snacks & Meal Prep | K6: blender | M6: B0855B5Z6F | N6: https://www.amazon.com/dp/B0855B5Z6F?tag=screenfreet0f-20
A7: 6 | B7: nutribullet Pro+ Personal Blender | C7: 112.5 | D7: 4.5 | E7: 11900 | F7: 10K+ | G7: $100-249 | H7: Athlete meals (blenders) | I7: All sports | J7: Teen Athlete Meals, Snacks & Meal Prep | K7: blender | M7: B0BS76NRG3 | N7: https://www.amazon.com/dp/B0BS76NRG3?tag=screenfreet0f-20
A8: 7 | B8: Apple Watch SE 3 GPS 40mm | C8: 239.99 | D8: 4.7 | E8: 4800 | F8: 10K+ | G8: $100-249 | H8: Tech gifts | I8: All sports | J8: Sports Mom Gifts & Gift Baskets | K8: apple watch | M8: B0HJ9ZNRKT | N8: https://www.amazon.com/dp/B0HJ9ZNRKT?tag=screenfreet0f-20
A9: 8 | B9: Apple AirPods Max 2 | C9: 474.99 | D9: 4.5 | E9: 1100 | F9: 10K+ | G9: $250-499 | H9: Tech gifts | I9: All sports | J9: Sports Mom Gifts & Gift Baskets | K9: airpods | M9: B0GSS4SGZR | N9: https://www.amazon.com/dp/B0GSS4SGZR?tag=screenfreet0f-20
A10: 9 | B10: Apple AirPods 5 with Noise Cancellation | C10: 149 | D10: 4.5 | E10: 438 | F10: 10K+ | G10: $100-249 | H10: Tech gifts | I10: All sports | J10: Sports Mom Gifts & Gift Baskets | K10: airpods | L10: Yes | M10: B0HJB76H2V | N10: https://www.amazon.com/dp/B0HJB76H2V?tag=screenfreet0f-20
A11: 10 | B11: Apple Watch Series 12 GPS 42mm | C11: 389.99 | D11: 4.7 | E11: 334 | F11: 10K+ | G11: $250-499 | H11: Tech gifts | I11: All sports | J11: Sports Mom Gifts & Gift Baskets | K11: apple watch | M11: B0HJ9ZXCSD | N11: https://www.amazon.com/dp/B0HJ9ZXCSD?tag=screenfreet0f-20
A12: 11 | B12: Ninja Professional Blender 2.0 | C12: 109.99 | D12: 4.7 | E12: 48300 | F12: 8K+ | G12: $100-249 | H12: Athlete meals (blenders) | I12: All sports | J12: Teen Athlete Meals, Snacks & Meal Prep | K12: blender | M12: B0CKTYP1JT | N12: https://www.amazon.com/dp/B0CKTYP1JT?tag=screenfreet0f-20
A13: 12 | B13: Jackery Explorer 300 Portable Power Station | C13: 289 | D13: 4.6 | E13: 11300 | F13: 8K+ | G13: $250-499 | H13: Tailgate & power | I13: All sports | J13: Sports Dad Essentials & Gifts | K13: power station | L13: Yes | M13: B082TMBYR6 | N13: https://www.amazon.com/dp/B082TMBYR6?tag=screenfreet0f-20
A14: 13 | B14: Garmin Forerunner 165 Running Smartwatch | C14: 192.49 | D14: 4.6 | E14: 5300 | F14: 7K+ | G14: $100-249 | H14: Tech gifts | I14: All sports | J14: Sports Mom Gifts & Gift Baskets | K14: garmin watch | L14: Yes | M14: B0CT3SGHXL | N14: https://www.amazon.com/dp/B0CT3SGHXL?tag=screenfreet0f-20
A15: 14 | B15: Theragun Relief Massage Gun | C15: 159.99 | D15: 4.5 | E15: 2600 | F15: 6K+ | G15: $100-249 | H15: Recovery | I15: All sports | J15: Sports Mom Gifts & Gift Baskets | K15: massage gun | L15: Yes | M15: B0CNS894RH | N15: https://www.amazon.com/dp/B0CNS894RH?tag=screenfreet0f-20
A16: 15 | B16: Bose SoundLink Flex Bluetooth Speaker (2nd Gen) | C16: 149 | D16: 4.7 | E16: 13600 | F16: 5K+ | G16: $100-249 | H16: Tailgate & power | I16: All sports | J16: Sports Dad Essentials & Gifts | K16: bluetooth speaker | M16: B0D6WD2QSQ | N16: https://www.amazon.com/dp/B0D6WD2QSQ?tag=screenfreet0f-20
A17: 16 | B17: Skullcandy Crusher ANC 2 Headphones | C17: 213.41 | D17: 4.6 | E17: 4800 | F17: 5K+ | G17: $100-249 | H17: Tech gifts | I17: All sports | J17: Sports Mom Gifts & Gift Baskets | K17: noise cancelling headphones | M17: B0C9L8ZR6Q | N17: https://www.amazon.com/dp/B0C9L8ZR6Q?tag=screenfreet0f-20
A18: 17 | B18: Callaway 300 Pro Golf Laser Rangefinder | C18: 194.95 | D18: 4.6 | E18: 12200 | F18: 4K+ | G18: $100-249 | H18: Golf (sports dad gifts) | I18: Golf | J18: Sports Dad Essentials & Gifts | K18: golf launch monitor | M18: B01KP195PY | N18: https://www.amazon.com/dp/B01KP195PY?tag=screenfreet0f-20
A19: 18 | B19: UGG Women's Tasman II Slipper | C19: 129.95 | D19: 4.7 | E19: 3900 | F19: 4K+ | G19: $100-249 | H19: Cold-weather gear | I19: All sports | J19: Cold Football Game Essentials | K19: ugg boots | M19: B0DPJH8ZRQ | N19: https://www.amazon.com/dp/B0DPJH8ZRQ?tag=screenfreet0f-20
A20: 19 | B20: DJI Osmo Action 4 Essential Combo | C20: 229 | D20: 4.7 | E20: 2500 | F20: 4K+ | G20: $100-249 | H20: Filming the game | I20: All sports | J20: Sports Mom Gifts & Gift Baskets | K20: action camera | M20: B0DS2B3P2B | N20: https://www.amazon.com/dp/B0DS2B3P2B?tag=screenfreet0f-20
A21: 20 | B21: EUHOMY Nugget Ice Maker with Carry Handle | C21: 147.16 | D21: 4.6 | E21: 1700 | F21: 4K+ | G21: $100-249 | H21: Coolers & drinks | I21: All sports | J21: Travel Ball & Tournament Must Haves | K21: portable ice maker | M21: B0GXB42S3F | N21: https://www.amazon.com/dp/B0GXB42S3F?tag=screenfreet0f-20
A22: 21 | B22: BLUETTI Elite 30 V2 Portable Power Station | C22: 279.99 | D22: 4.5 | E22: 1200 | F22: 4K+ | G22: $250-499 | H22: Tailgate & power | I22: All sports | J22: Sports Dad Essentials & Gifts | K22: power station | M22: B0F42HLLSC | N22: https://www.amazon.com/dp/B0F42HLLSC?tag=screenfreet0f-20
A23: 22 | B23: BowFlex SelectTech 840 Adjustable Kettlebell | C23: 149 | D23: 4.8 | E23: 7700 | F23: 3K+ | G23: $100-249 | H23: Backyard & home training | I23: All sports | J23: Backyard Sports Training Equipment | K23: adjustable dumbbells | M23: B07X64MXBS | N23: https://www.amazon.com/dp/B07X64MXBS?tag=screenfreet0f-20
A24: 23 | B24: Jackery Explorer 1000 v2 Power Station | C24: 559 | D24: 4.7 | E24: 3700 | F24: 3K+ | G24: $500-999 | H24: Tailgate & power | I24: All sports | J24: Sports Dad Essentials & Gifts | K24: power station | L24: Yes | M24: B0D7PPG25F | N24: https://www.amazon.com/dp/B0D7PPG25F?tag=screenfreet0f-20
A25: 24 | B25: Apple iPad mini (A17 Pro) | C25: 559.99 | D25: 4.7 | E25: 3400 | F25: 3K+ | G25: $500-999 | H25: Tech gifts | I25: All sports | J25: Sports Mom Gifts & Gift Baskets | K25: ipad | M25: B0DK3W6TV6 | N25: https://www.amazon.com/dp/B0DK3W6TV6?tag=screenfreet0f-20
A26: 25 | B26: Apple Watch SE 3 GPS + Cellular 40mm | C26: 299 | D26: 4.6 | E26: 625 | F26: 3K+ | G26: $250-499 | H26: Tech gifts | I26: All sports | J26: Sports Mom Gifts & Gift Baskets | K26: apple watch | M26: B0HJB73N19 | N26: https://www.amazon.com/dp/B0HJB73N19?tag=screenfreet0f-20
A27: 26 | B27: BowFlex SelectTech Adjustable Dumbbells | C27: 399.99 | D27: 4.8 | E27: 334 | F27: 3K+ | G27: $250-499 | H27: Backyard & home training | I27: All sports | J27: Backyard Sports Training Equipment | K27: adjustable dumbbells | L27: Yes | M27: B0FRNG2N5H | N27: https://www.amazon.com/dp/B0FRNG2N5H?tag=screenfreet0f-20
A28: 27 | B28: The North Face Borealis Backpack | C28: 115 | D28: 4.7 | E28: 16500 | F28: 2K+ | G28: $100-249 | H28: Bags | I28: All sports | J28: Game Day Bags & Stadium Bags | K28: backpack sports | M28: B0CN9SD8JF | N28: https://www.amazon.com/dp/B0CN9SD8JF?tag=screenfreet0f-20
A29: 28 | B29: CROWN SHADES 10x10 Pop Up Canopy | C29: 139.99 | D29: 4.6 | E29: 11500 | F29: 2K+ | G29: $100-249 | H29: Canopies & shade | I29: All sports | J29: Travel Ball & Tournament Must Haves | K29: canopy with sidewalls | L29: Yes | M29: B078XR1CS8 | N29: https://www.amazon.com/dp/B078XR1CS8?tag=screenfreet0f-20
A30: 29 | B30: Theragun Prime 6th Gen Massage Gun | C30: 329.99 | D30: 4.6 | E30: 6800 | F30: 2K+ | G30: $250-499 | H30: Recovery | I30: All sports | J30: Sports Mom Gifts & Gift Baskets | K30: massage gun | M30: B0FKCJNHWB | N30: https://www.amazon.com/dp/B0FKCJNHWB?tag=screenfreet0f-20
A31: 30 | B31: DJI Osmo Action 4 Standard Combo | C31: 239 | D31: 4.6 | E31: 5200 | F31: 2K+ | G31: $100-249 | H31: Filming the game | I31: All sports | J31: Sports Mom Gifts & Gift Baskets | K31: action camera | M31: B0C783YNW7 | N31: https://www.amazon.com/dp/B0C783YNW7?tag=screenfreet0f-20
A32: 31 | B32: CROWN SHADES 10x10 Pop Up Canopy with 1 Side Wall | C32: 149.99 | D32: 4.6 | E32: 4500 | F32: 2K+ | G32: $100-249 | H32: Canopies & shade | I32: All sports | J32: Travel Ball & Tournament Must Haves | K32: canopy with sidewalls | M32: B09KLVB9X7 | N32: https://www.amazon.com/dp/B09KLVB9X7?tag=screenfreet0f-20
A33: 32 | B33: Blackstone 1883 Original 28" Griddle with Hood | C33: 399 | D33: 4.7 | E33: 2000 | F33: 2K+ | G33: $250-499 | H33: Tailgate & power | I33: All sports | J33: Sports Dad Essentials & Gifts | K33: griddle | M33: B08BWWKKKL | N33: https://www.amazon.com/dp/B08BWWKKKL?tag=screenfreet0f-20
A34: 33 | B34: Theragun Mini 3rd Gen | C34: 219.99 | D34: 4.6 | E34: 1900 | F34: 2K+ | G34: $100-249 | H34: Recovery | I34: All sports | J34: Sports Mom Gifts & Gift Baskets | K34: massage gun | L34: Yes | M34: B0DV7JN7ZD | N34: https://www.amazon.com/dp/B0DV7JN7ZD?tag=screenfreet0f-20
A35: 34 | B35: Anker SOLIX C1000 Gen 2 Power Station | C35: 499.99 | D35: 4.7 | E35: 1700 | F35: 2K+ | G35: $250-499 | H35: Tailgate & power | I35: All sports | J35: Sports Dad Essentials & Gifts | K35: power station | M35: B0FN7MSY4L | N35: https://www.amazon.com/dp/B0FN7MSY4L?tag=screenfreet0f-20
A36: 35 | B36: Vortex Triumph HD 12x50 Binoculars | C36: 119 | D36: 4.7 | E36: 266 | F36: 2K+ | G36: $100-249 | H36: Filming the game | I36: All sports | J36: Sports Mom Gifts & Gift Baskets | K36: binoculars | M36: B0GNTHY8JK | N36: https://www.amazon.com/dp/B0GNTHY8JK?tag=screenfreet0f-20
A37: 36 | B37: Opove M3 Pro 2 Massage Gun | C37: 129.99 | D37: 4.7 | E37: 20400 | F37: 1K+ | G37: $100-249 | H37: Recovery | I37: All sports | J37: Sports Mom Gifts & Gift Baskets | K37: massage gun | M37: B07TWFK7JW | N37: https://www.amazon.com/dp/B07TWFK7JW?tag=screenfreet0f-20
A38: 37 | B38: FLEXIMOUNTS 4x8 Overhead Garage Storage Rack | C38: 145.99 | D38: 4.7 | E38: 19300 | F38: 1K+ | G38: $100-249 | H38: Car & garage storage | I38: All sports | J38: Sports Equipment Storage & Garage Organization | K38: garage storage system | L38: Yes | M38: B0194R5BSA | N38: https://www.amazon.com/dp/B0194R5BSA?tag=screenfreet0f-20
A39: 38 | B39: JBL Xtreme 2 Waterproof Bluetooth Speaker | C39: 199.99 | D39: 4.7 | E39: 15500 | F39: 1K+ | G39: $100-249 | H39: Tailgate & power | I39: All sports | J39: Sports Dad Essentials & Gifts | K39: bluetooth speaker | M39: B07CVPZJTV | N39: https://www.amazon.com/dp/B07CVPZJTV?tag=screenfreet0f-20
A40: 39 | B40: DJI Osmo Mobile 8 + Mic Mini Transmitter | C40: 182 | D40: 4.6 | E40: 14200 | F40: 1K+ | G40: $100-249 | H40: Filming the game | I40: All sports | J40: Sports Mom Gifts & Gift Baskets | K40: gimbal stabilizer | M40: B0GR9YG1LY | N40: https://www.amazon.com/dp/B0GR9YG1LY?tag=screenfreet0f-20
A41: 40 | B41: Igloo Polar Hard Cooler | C41: 115.99 | D41: 4.6 | E41: 11500 | F41: 1K+ | G41: $100-249 | H41: Coolers & drinks | I41: All sports | J41: Travel Ball & Tournament Must Haves | K41: cooler | L41: Yes | M41: B004QILD6W | N41: https://www.amazon.com/dp/B004QILD6W?tag=screenfreet0f-20
A42: 41 | B42: ORORO Women's Heated Vest | C42: 129.99 | D42: 4.5 | E42: 11100 | F42: 1K+ | G42: $100-249 | H42: Cold-weather gear | I42: All sports | J42: Cold Football Game Essentials | K42: heated jacket | L42: Yes | M42: B01H50RF46 | N42: https://www.amazon.com/dp/B01H50RF46?tag=screenfreet0f-20
A43: 42 | B43: UGG Women's Classic Ultra Mini Boot | C43: 164.95 | D43: 4.5 | E43: 10400 | F43: 1K+ | G43: $100-249 | H43: Cold-weather gear | I43: All sports | J43: Cold Football Game Essentials | K43: ugg boots | M43: B082HHTKB6 | N43: https://www.amazon.com/dp/B082HHTKB6?tag=screenfreet0f-20
A44: 43 | B44: Garmin Forerunner 55 GPS Running Watch | C44: 158 | D44: 4.5 | E44: 10300 | F44: 1K+ | G44: $100-249 | H44: Tech gifts | I44: All sports | J44: Sports Mom Gifts & Gift Baskets | K44: garmin watch | L44: Yes | M44: B0953X73TP | N44: https://www.amazon.com/dp/B0953X73TP?tag=screenfreet0f-20
A45: 44 | B45: Insta360 X3 360 Action Camera | C45: 299.99 | D45: 4.6 | E45: 6800 | F45: 1K+ | G45: $250-499 | H45: Filming the game | I45: All sports | J45: Sports Mom Gifts & Gift Baskets | K45: action camera | L45: Yes | M45: B0B9H572LC | N45: https://www.amazon.com/dp/B0B9H572LC?tag=screenfreet0f-20
A46: 45 | B46: Blackstone 1666 22" Tabletop Griddle | C46: 178.99 | D46: 4.7 | E46: 6800 | F46: 1K+ | G46: $100-249 | H46: Tailgate & power | I46: All sports | J46: Sports Dad Essentials & Gifts | K46: griddle | M46: B076MFM8LX | N46: https://www.amazon.com/dp/B076MFM8LX?tag=screenfreet0f-20
A47: 46 | B47: FLEXIMOUNTS 2-Pack 2x6 ft Wall Garage Shelving | C47: 135.98 | D47: 4.7 | E47: 5300 | F47: 1K+ | G47: $100-249 | H47: Car & garage storage | I47: All sports | J47: Sports Equipment Storage & Garage Organization | K47: garage storage system | M47: B01LYQGF4M | N47: https://www.amazon.com/dp/B01LYQGF4M?tag=screenfreet0f-20
A48: 47 | B48: Soundcore Boom 2 Plus Bluetooth Speaker | C48: 169.99 | D48: 4.5 | E48: 5200 | F48: 1K+ | G48: $100-249 | H48: Tailgate & power | I48: All sports | J48: Sports Dad Essentials & Gifts | K48: bluetooth speaker | M48: B0CZ7DY692 | N48: https://www.amazon.com/dp/B0CZ7DY692?tag=screenfreet0f-20
A49: 48 | B49: Ninja Foodi TWISTi Blender DUO | C49: 119.94 | D49: 4.5 | E49: 4600 | F49: 1K+ | G49: $100-249 | H49: Athlete meals (blenders) | I49: All sports | J49: Teen Athlete Meals, Snacks & Meal Prep | K49: blender | M49: B09SBRGSFH | N49: https://www.amazon.com/dp/B09SBRGSFH?tag=screenfreet0f-20
A50: 49 | B50: UGG Women's Cozy Slipper | C50: 129.95 | D50: 4.8 | E50: 4400 | F50: 1K+ | G50: $100-249 | H50: Cold-weather gear | I50: All sports | J50: Cold Football Game Essentials | K50: ugg boots | M50: B084485683 | N50: https://www.amazon.com/dp/B084485683?tag=screenfreet0f-20
A51: 50 | B51: Vortex Crossfire HD 10x42 Binoculars | C51: 149 | D51: 4.8 | E51: 4000 | F51: 1K+ | G51: $100-249 | H51: Filming the game | I51: All sports | J51: Sports Mom Gifts & Gift Baskets | K51: binoculars | M51: B07V3LB5DN | N51: https://www.amazon.com/dp/B07V3LB5DN?tag=screenfreet0f-20
A52: 51 | B52: Coleman Triton 2-Burner Propane Stove | C52: 119.99 | D52: 4.7 | E52: 3700 | F52: 1K+ | G52: $100-249 | H52: Tailgate & power | I52: All sports | J52: Sports Dad Essentials & Gifts | K52: camping stove | M52: B09HN1C1YJ | N52: https://www.amazon.com/dp/B09HN1C1YJ?tag=screenfreet0f-20
A53: 52 | B53: Timber Ridge 400L Double Decker Wagon with Brakes | C53: 124.99 | D53: 4.6 | E53: 3600 | F53: 1K+ | G53: $100-249 | H53: Wagons | I53: All sports | J53: Sports Wagon Ideas & Accessories | K53: wagon collapsible | L53: Yes | M53: B0G23XKMJL | N53: https://www.amazon.com/dp/B0G23XKMJL?tag=screenfreet0f-20
A54: 53 | B54: Canon EOS Rebel T7 DSLR Double Zoom Lens Kit | C54: 619 | D54: 4.7 | E54: 3200 | F54: 1K+ | G54: $500-999 | H54: Filming the game | I54: All sports | J54: Sports Mom Gifts & Gift Baskets | K54: camera lens telephoto | L54: Yes | M54: B0101RW3QK | N54: https://www.amazon.com/dp/B0101RW3QK?tag=screenfreet0f-20
A55: 54 | B55: Sony ULT Field 1 Waterproof Bluetooth Speaker | C55: 108 | D55: 4.7 | E55: 2900 | F55: 1K+ | G55: $100-249 | H55: Tailgate & power | I55: All sports | J55: Sports Dad Essentials & Gifts | K55: bluetooth speaker | M55: B0CXKSCY1G | N55: https://www.amazon.com/dp/B0CXKSCY1G?tag=screenfreet0f-20
A56: 55 | B56: BLUETTI AC180 Portable Power Station | C56: 499 | D56: 4.5 | E56: 2800 | F56: 1K+ | G56: $250-499 | H56: Tailgate & power | I56: All sports | J56: Sports Dad Essentials & Gifts | K56: power station | M56: B0C1SMJTDT | N56: https://www.amazon.com/dp/B0C1SMJTDT?tag=screenfreet0f-20
A57: 56 | B57: Blackstone 1813 22" Tabletop Griddle with Hood | C57: 219 | D57: 4.7 | E57: 2800 | F57: 1K+ | G57: $100-249 | H57: Tailgate & power | I57: All sports | J57: Sports Dad Essentials & Gifts | K57: griddle | L57: Yes | M57: B07ZS5RQZ4 | N57: https://www.amazon.com/dp/B07ZS5RQZ4?tag=screenfreet0f-20
A58: 57 | B58: PowerBlock Elite EXP 90 Adjustable Dumbbells | C58: 399 | D58: 4.6 | E58: 2600 | F58: 1K+ | G58: $250-499 | H58: Backyard & home training | I58: All sports | J58: Backyard Sports Training Equipment | K58: adjustable dumbbells | M58: B00A21NRNO | N58: https://www.amazon.com/dp/B00A21NRNO?tag=screenfreet0f-20
A59: 58 | B59: Insta360 X5 8K 360 Action Camera | C59: 549.99 | D59: 4.6 | E59: 2600 | F59: 1K+ | G59: $500-999 | H59: Filming the game | I59: All sports | J59: Sports Mom Gifts & Gift Baskets | K59: action camera | M59: B0DZCBYCNY | N59: https://www.amazon.com/dp/B0DZCBYCNY?tag=screenfreet0f-20
A60: 59 | B60: EUHOMY 19QT 12V Electric Cooler/Fridge | C60: 138.88 | D60: 4.5 | E60: 2400 | F60: 1K+ | G60: $100-249 | H60: Coolers & drinks | I60: All sports | J60: Travel Ball & Tournament Must Haves | K60: cooler | M60: B0C4H82CHZ | N60: https://www.amazon.com/dp/B0C4H82CHZ?tag=screenfreet0f-20
A61: 60 | B61: DJI Osmo Action 6 Enhanced Combo | C61: 496 | D61: 4.5 | E61: 2400 | F61: 1K+ | G61: $250-499 | H61: Filming the game | I61: All sports | J61: Sports Mom Gifts & Gift Baskets | K61: action camera | M61: B0FNMPZ1RS | N61: https://www.amazon.com/dp/B0FNMPZ1RS?tag=screenfreet0f-20
A62: 61 | B62: JBL PartyBox Club 120 Portable Party Speaker | C62: 349.95 | D62: 4.7 | E62: 2200 | F62: 1K+ | G62: $250-499 | H62: Tailgate & power | I62: All sports | J62: Sports Dad Essentials & Gifts | K62: bluetooth speaker | M62: B0CTD6WMXT | N62: https://www.amazon.com/dp/B0CTD6WMXT?tag=screenfreet0f-20
A63: 62 | B63: Turtlebox Ranger Waterproof Bluetooth Speaker | C63: 250 | D63: 4.6 | E63: 2000 | F63: 1K+ | G63: $250-499 | H63: Tailgate & power | I63: All sports | J63: Sports Dad Essentials & Gifts | K63: bluetooth speaker | M63: B0F2JHSGCJ | N63: https://www.amazon.com/dp/B0F2JHSGCJ?tag=screenfreet0f-20
A64: 63 | B64: NordicTrack 55 lb Select-a-Weight Dumbbells | C64: 399 | D64: 4.5 | E64: 1900 | F64: 1K+ | G64: $250-499 | H64: Backyard & home training | I64: All sports | J64: Backyard Sports Training Equipment | K64: adjustable dumbbells | M64: B08BDD6GPC | N64: https://www.amazon.com/dp/B08BDD6GPC?tag=screenfreet0f-20
A65: 64 | B65: DJI Osmo Action 5 Pro Combo | C65: 309 | D65: 4.6 | E65: 1900 | F65: 1K+ | G65: $250-499 | H65: Filming the game | I65: All sports | J65: Sports Mom Gifts & Gift Baskets | K65: sports camera ai tracking | L65: Yes | M65: B0DS2DF5S5 | N65: https://www.amazon.com/dp/B0DS2DF5S5?tag=screenfreet0f-20
A66: 65 | B66: Marshall Emberton III Waterproof Speaker | C66: 179.99 | D66: 4.7 | E66: 1800 | F66: 1K+ | G66: $100-249 | H66: Tailgate & power | I66: All sports | J66: Sports Dad Essentials & Gifts | K66: bluetooth speaker | M66: B0DT1CZ58V | N66: https://www.amazon.com/dp/B0DT1CZ58V?tag=screenfreet0f-20
A67: 66 | B67: Anker SOLIX C300 DC Power Station | C67: 189.99 | D67: 4.5 | E67: 1700 | F67: 1K+ | G67: $100-249 | H67: Tailgate & power | I67: All sports | J67: Sports Dad Essentials & Gifts | K67: power station | M67: B0D62PMB3R | N67: https://www.amazon.com/dp/B0D62PMB3R?tag=screenfreet0f-20
A68: 67 | B68: UGG Women's Tazz II | C68: 149.95 | D68: 4.7 | E68: 1600 | F68: 1K+ | G68: $100-249 | H68: Cold-weather gear | I68: All sports | J68: Cold Football Game Essentials | K68: ugg boots | M68: B0DPJJ6LLC | N68: https://www.amazon.com/dp/B0DPJJ6LLC?tag=screenfreet0f-20
A69: 68 | B69: Keter Stack N Roll Modular Storage System | C69: 118.99 | D69: 4.6 | E69: 1500 | F69: 1K+ | G69: $100-249 | H69: Car & garage storage | I69: All sports | J69: Sports Equipment Storage & Garage Organization | K69: garage storage system | M69: B0CSQYFQ5C | N69: https://www.amazon.com/dp/B0CSQYFQ5C?tag=screenfreet0f-20
A70: 69 | B70: Originsure 300L Big-Wheel Collapsible Wagon | C70: 119.99 | D70: 4.5 | E70: 1400 | F70: 1K+ | G70: $100-249 | H70: Wagons | I70: All sports | J70: Sports Wagon Ideas & Accessories | K70: wagon collapsible | L70: Yes | M70: B0DPH1F6ZY | N70: https://www.amazon.com/dp/B0DPH1F6ZY?tag=screenfreet0f-20
A71: 70 | B71: EcoFlow Delta 3 Classic Power Station | C71: 499 | D71: 4.7 | E71: 1300 | F71: 1K+ | G71: $250-499 | H71: Tailgate & power | I71: All sports | J71: Sports Dad Essentials & Gifts | K71: power station | M71: B0FQVC4RF5 | N71: https://www.amazon.com/dp/B0FQVC4RF5?tag=screenfreet0f-20
A72: 71 | B72: Portable Basketball Hoop 5.6-10 ft Adjustable | C72: 159.99 | D72: 4.5 | E72: 1200 | F72: 1K+ | G72: $100-249 | H72: Backyard & home training | I72: Basketball | J72: Backyard Sports Training Equipment | K72: basketball hoop portable | L72: Yes | M72: B0GJRYPQ3D | N72: https://www.amazon.com/dp/B0GJRYPQ3D?tag=screenfreet0f-20
A73: 72 | B73: GoPro HERO12 Black Action Camera | C73: 294.99 | D73: 4.5 | E73: 1000 | F73: 1K+ | G73: $250-499 | H73: Filming the game | I73: All sports | J73: Sports Mom Gifts & Gift Baskets | K73: action camera | M73: B0CZMG5L6X | N73: https://www.amazon.com/dp/B0CZMG5L6X?tag=screenfreet0f-20
A74: 73 | B74: Garmin Instinct 3 AMOLED Rugged Smartwatch | C74: 349 | D74: 4.6 | E74: 924 | F74: 1K+ | G74: $250-499 | H74: Tech gifts | I74: All sports | J74: Sports Mom Gifts & Gift Baskets | K74: garmin watch | M74: B0DSC8JF59 | N74: https://www.amazon.com/dp/B0DSC8JF59?tag=screenfreet0f-20
A75: 74 | B75: SurviveX Large First Aid Kit | C75: 124.99 | D75: 4.8 | E75: 919 | F75: 1K+ | G75: $100-249 | H75: Team mom & coach | I75: All sports | J75: Coach Gifts & Team Mom Ideas | K75: first aid kit | M75: B0DF3LXT66 | N75: https://www.amazon.com/dp/B0DF3LXT66?tag=screenfreet0f-20
A76: 75 | B76: Bushnell Tour V6 Shift Laser Rangefinder | C76: 299.99 | D76: 4.7 | E76: 638 | F76: 1K+ | G76: $250-499 | H76: Backyard & home training | I76: Golf | J76: Backyard Sports Training Equipment | K76: golf launch monitor | M76: B0C4TNKZFG | N76: https://www.amazon.com/dp/B0C4TNKZFG?tag=screenfreet0f-20
A77: 76 | B77: FDB2 Adjustable Dumbbell Set of 2 | C77: 139.99 | D77: 4.8 | E77: 635 | F77: 1K+ | G77: $100-249 | H77: Backyard & home training | I77: All sports | J77: Backyard Sports Training Equipment | K77: adjustable dumbbells | L77: Yes | M77: B0DK3H169C | N77: https://www.amazon.com/dp/B0DK3H169C?tag=screenfreet0f-20
A78: 77 | B78: Adjustable Dumbbell Set Pair 25/50 lb | C78: 239.99 | D78: 4.5 | E78: 164 | F78: 1K+ | G78: $100-249 | H78: Backyard & home training | I78: All sports | J78: Backyard Sports Training Equipment | K78: adjustable dumbbells | M78: B0GJ4HT8SS | N78: https://www.amazon.com/dp/B0GJ4HT8SS?tag=screenfreet0f-20
A79: 78 | B79: Coleman Classic Wheeled Cooler | C79: 109.99 | D79: 4.5 | E79: 9700 | F79: 900+ | G79: $100-249 | H79: Coolers & drinks | I79: All sports | J79: Travel Ball & Tournament Must Haves | K79: cooler | M79: B0GRWNHL76 | N79: https://www.amazon.com/dp/B0GRWNHL76?tag=screenfreet0f-20
A80: 79 | B80: Mr. Heater 18,000 BTU Big Buddy Heater | C80: 155.98 | D80: 4.6 | E80: 5700 | F80: 900+ | G80: $100-249 | H80: Cold-weather gear | I80: All sports | J80: Cold Football Game Essentials | K80: propane heater portable | M80: B07Q82MG8S | N80: https://www.amazon.com/dp/B07Q82MG8S?tag=screenfreet0f-20
A81: 80 | B81: Lifepro Adjustable Dumbbells | C81: 189.99 | D81: 4.6 | E81: 3300 | F81: 900+ | G81: $100-249 | H81: Backyard & home training | I81: All sports | J81: Backyard Sports Training Equipment | K81: adjustable dumbbells | M81: B08QTGV9BW | N81: https://www.amazon.com/dp/B08QTGV9BW?tag=screenfreet0f-20
A82: 81 | B82: Theragun Prime Plus Heated Massage Gun | C82: 429.99 | D82: 4.6 | E82: 6800 | F82: 800+ | G82: $250-499 | H82: Recovery | I82: All sports | J82: Sports Mom Gifts & Gift Baskets | K82: massage gun | M82: B0DD1YS393 | N82: https://www.amazon.com/dp/B0DD1YS393?tag=screenfreet0f-20
A83: 82 | B83: Mr. Heater 18,000 BTU Big Buddy PRO Heater | C83: 159 | D83: 4.6 | E83: 3500 | F83: 800+ | G83: $100-249 | H83: Cold-weather gear | I83: All sports | J83: Cold Football Game Essentials | K83: patio heater portable | M83: B0002WRHE8 | N83: https://www.amazon.com/dp/B0002WRHE8?tag=screenfreet0f-20
A84: 83 | B84: BORNOON Shoe Cabinet with 3 Flip Drawers | C84: 119.99 | D84: 4.6 | E84: 3200 | F84: 800+ | G84: $100-249 | H84: Car & garage storage | I84: All sports | J84: Sports Equipment Storage & Garage Organization | K84: shoe rack | M84: B0CBRBVL61 | N84: https://www.amazon.com/dp/B0CBRBVL61?tag=screenfreet0f-20
A85: 84 | B85: Vortex Crossfire HD 12x50 Binoculars | C85: 179 | D85: 4.8 | E85: 3200 | F85: 800+ | G85: $100-249 | H85: Filming the game | I85: All sports | J85: Sports Mom Gifts & Gift Baskets | K85: binoculars | M85: B07V4M7LTY | N85: https://www.amazon.com/dp/B07V4M7LTY?tag=screenfreet0f-20
A86: 85 | B86: ASK ECHO T-Lock Golf Cart Bag | C86: 179.99 | D86: 4.6 | E86: 2900 | F86: 800+ | G86: $100-249 | H86: Golf (sports dad gifts) | I86: Golf | J86: Sports Dad Essentials & Gifts | K86: golf cart | M86: B09NC7WHVR | N86: https://www.amazon.com/dp/B09NC7WHVR?tag=screenfreet0f-20
A87: 86 | B87: Iwatani 35FW Portable Butane Cooktop | C87: 129.99 | D87: 4.7 | E87: 2100 | F87: 800+ | G87: $100-249 | H87: Tailgate & power | I87: All sports | J87: Sports Dad Essentials & Gifts | K87: camping stove | M87: B00522F2R2 | N87: https://www.amazon.com/dp/B00522F2R2?tag=screenfreet0f-20
A88: 87 | B88: ERIC FLAG 40 lb Adjustable Weighted Vest | C88: 159.99 | D88: 4.7 | E88: 1100 | F88: 800+ | G88: $100-249 | H88: Backyard & home training | I88: All sports | J88: Backyard Sports Training Equipment | K88: weighted vest | M88: B09WB1BF81 | N88: https://www.amazon.com/dp/B09WB1BF81?tag=screenfreet0f-20
A89: 88 | B89: Oversized Padded Camping Chairs (2 pack) | C89: 119.99 | D89: 4.5 | E89: 473 | F89: 800+ | G89: $100-249 | H89: Seats & chairs | I89: All sports | J89: Stadium Seats & Bleacher Comfort | K89: rocking camping chair | M89: B0FLY4FVQP | N89: https://www.amazon.com/dp/B0FLY4FVQP?tag=screenfreet0f-20
... A97: 96 | B97: Harppa Remy Wagon Stroller for 2 Kids | C97: 249.99 | D97: 4.8 | E97: 148 | F97: 700+ | G97: $100-249 | H97: Wagons | I97: All sports | J97: Sports Wagon Ideas & Accessories | K97: stroller wagon | M97: B0G3PB2RC5 | N97: https://www.amazon.com/dp/B0G3PB2RC5?tag=screenfreet0f-20
A98: 97 | B98: SKLZ Hurricane Baseball and Softball Swing Trainer | C98: 149.99 | D98: 4.7 | E98: 5100 | F98: 600+ | G98: $100-249 | H98: Backyard & home training | I98: Softball | J98: Backyard Sports Training Equipment | K98: softball pitching machine | L98: Yes | M98: B002MA7Y1Y | N98: https://www.amazon.com/dp/B002MA7Y1Y?tag=screenfreet0f-20
A99: 98 | B99: CAP Power Rack Stand with Pull-Up Bar | C99: 119.99 | D99: 4.5 | E99: 4500 | F99: 600+ | G99: $100-249 | H99: Backyard & home training | I99: All sports | J99: Backyard Sports Training Equipment | K99: squat rack | M99: B00HYQP72O | N99: https://www.amazon.com/dp/B00HYQP72O?tag=screenfreet0f-20
A100: 99 | B100: Igloo Maxcold Glide 110 Qt Wheeled Cooler | C100: 169.99 | D100: 4.6 | E100: 3000 | F100: 600+ | G100: $100-249 | H100: Coolers & drinks | I100: All sports | J100: Travel Ball & Tournament Must Haves | K100: cooler | M100: B004XUNDX4 | N100: https://www.amazon.com/dp/B004XUNDX4?tag=screenfreet0f-20
A101: 100 | B101: Blackstone 1814 17" Propane Griddle | C101: 159.99 | D101: 4.7 | E101: 2200 | F101: 600+ | G101: $100-249 | H101: Tailgate & power | I101: All sports | J101: Sports Dad Essentials & Gifts | K101: griddle | M101: B07ZS5HWCC | N101: https://www.amazon.com/dp/B07ZS5HWCC?tag=screenfreet0f-20
A102: 101 | B102: Vortex Crossfire HD 8x42 Binoculars | C102: 139 | D102: 4.8 | E102: 1300 | F102: 600+ | G102: $100-249 | H102: Filming the game | I102: All sports | J102: Sports Mom Gifts & Gift Baskets | K102: binoculars | M102: B07V3L7P3P | N102: https://www.amazon.com/dp/B07V3L7P3P?tag=screenfreet0f-20
A103: 102 | B103: VIVOHOME Stadium Seats with Back Support | C103: 105.99 | D103: 4.7 | E103: 667 | F103: 600+ | G103: $100-249 | H103: Seats & chairs | I103: All sports | J103: Stadium Seats & Bleacher Comfort | K103: stadium chair | L103: Yes | M103: B0CWN7CKPN | N103: https://www.amazon.com/dp/B0CWN7CKPN?tag=screenfreet0f-20
A104: 103 | B104: Portable Propane Fire Pit 19" 60,000 BTU | C104: 109.99 | D104: 4.7 | E104: 460 | F104: 600+ | G104: $100-249 | H104: Cold-weather gear | I104: All sports | J104: Cold Football Game Essentials | K104: propane heater portable | M104: B00TQ6BZYY | N104: https://www.amazon.com/dp/B00TQ6BZYY?tag=screenfreet0f-20
A105: 104 | B105: 480 lb Heavy Duty All-Terrain Collapsible Wagon | C105: 104.99 | D105: 4.7 | E105: 236 | F105: 600+ | G105: $100-249 | H105: Wagons | I105: All sports | J105: Sports Wagon Ideas & Accessories | K105: wagon collapsible | M105: B0GMHD4G76 | N105: https://www.amazon.com/dp/B0GMHD4G76?tag=screenfreet0f-20
A106: 105 | B106: SurviveX Large Pro First Aid Kit | C106: 159.99 | D106: 4.8 | E106: 197 | F106: 600+ | G106: $100-249 | H106: Team mom & coach | I106: All sports | J106: Coach Gifts & Team Mom Ideas | K106: first aid kit | M106: B0FND43WYX | N106: https://www.amazon.com/dp/B0FND43WYX?tag=screenfreet0f-20
A107: 106 | B107: Harppa Remy XL Wagon Stroller for 4 Kids | C107: 349.89 | D107: 4.8 | E107: 148 | F107: 600+ | G107: $250-499 | H107: Wagons | I107: All sports | J107: Sports Wagon Ideas & Accessories | K107: stroller wagon | M107: B0GD1HQRZZ | N107: https://www.amazon.com/dp/B0GD1HQRZZ?tag=screenfreet0f-20
...

Sheet Summary
A1: Summary
A3: By category
A4: Group | B4: Products | C4: Best Bets
A5: Athlete meals (blenders) | B5: =COUNTIF('All Products'!H:H,A5) -> 5 | C5: =COUNTIF('Best Bets'!H:H,A5) -> 4
A6: Backyard & home training | B6: =COUNTIF('All Products'!H:H,A6) -> 358 | C6: =COUNTIF('Best Bets'!H:H,A6) -> 80
A7: Bags | B7: =COUNTIF('All Products'!H:H,A7) -> 55 | C7: =COUNTIF('Best Bets'!H:H,A7) -> 15
A8: Canopies & shade | B8: =COUNTIF('All Products'!H:H,A8) -> 22 | C8: =COUNTIF('Best Bets'!H:H,A8) -> 6
A9: Car & garage storage | B9: =COUNTIF('All Products'!H:H,A9) -> 32 | C9: =COUNTIF('Best Bets'!H:H,A9) -> 8
A10: Cold-weather gear | B10: =COUNTIF('All Products'!H:H,A10) -> 52 | C10: =COUNTIF('Best Bets'!H:H,A10) -> 25
A11: Coolers & drinks | B11: =COUNTIF('All Products'!H:H,A11) -> 38 | C11: =COUNTIF('Best Bets'!H:H,A11) -> 14
A12: Filming the game | B12: =COUNTIF('All Products'!H:H,A12) -> 42 | C12: =COUNTIF('Best Bets'!H:H,A12) -> 32
A13: Game room & arcade | B13: =COUNTIF('All Products'!H:H,A13) -> 5 | C13: =COUNTIF('Best Bets'!H:H,A13) -> 0
A14: Gifts for kids & teens | B14: =COUNTIF('All Products'!H:H,A14) -> 5 | C14: =COUNTIF('Best Bets'!H:H,A14) -> 0
A15: Golf (sports dad gifts) | B15: =COUNTIF('All Products'!H:H,A15) -> 27 | C15: =COUNTIF('Best Bets'!H:H,A15) -> 12
A16: Mom style | B16: =COUNTIF('All Products'!H:H,A16) -> 9 | C16: =COUNTIF('Best Bets'!H:H,A16) -> 4
... A24: Wagons | B24: =COUNTIF('All Products'!H:H,A24) -> 24 | C24: =COUNTIF('Best Bets'!H:H,A24) -> 12
A25: Total | B25: =SUM(B5:B24) -> 959 | C25: =SUM(C5:C24) -> 302
A27: By sport
A28: Group | B28: Products | C28: Best Bets
A29: All sports | B29: =COUNTIF('All Products'!I:I,A29) -> 464 | C29: =COUNTIF('Best Bets'!I:I,A29) -> 223
A30: Baseball | B30: =COUNTIF('All Products'!I:I,A30) -> 126 | C30: =COUNTIF('Best Bets'!I:I,A30) -> 14
A31: Basketball | B31: =COUNTIF('All Products'!I:I,A31) -> 83 | C31: =COUNTIF('Best Bets'!I:I,A31) -> 12
A32: Cheer | B32: =COUNTIF('All Products'!I:I,A32) -> 12 | C32: =COUNTIF('Best Bets'!I:I,A32) -> 2
A33: Dance | B33: =COUNTIF('All Products'!I:I,A33) -> 2 | C33: =COUNTIF('Best Bets'!I:I,A33) -> 0
A34: Football | B34: =COUNTIF('All Products'!I:I,A34) -> 21 | C34: =COUNTIF('Best Bets'!I:I,A34) -> 1
A35: Golf | B35: =COUNTIF('All Products'!I:I,A35) -> 33 | C35: =COUNTIF('Best Bets'!I:I,A35) -> 14
A36: Gymnastics | B36: =COUNTIF('All Products'!I:I,A36) -> 34 | C36: =COUNTIF('Best Bets'!I:I,A36) -> 13
A37: Hockey | B37: =COUNTIF('All Products'!I:I,A37) -> 31 | C37: =COUNTIF('Best Bets'!I:I,A37) -> 3
A38: Lacrosse | B38: =COUNTIF('All Products'!I:I,A38) -> 13 | C38: =COUNTIF('Best Bets'!I:I,A38) -> 0
A39: Pickleball | B39: =COUNTIF('All Products'!I:I,A39) -> 23 | C39: =COUNTIF('Best Bets'!I:I,A39) -> 6
A40: Soccer | B40: =COUNTIF('All Products'!I:I,A40) -> 48 | C40: =COUNTIF('Best Bets'!I:I,A40) -> 4
... A46: Wrestling | B46: =COUNTIF('All Products'!I:I,A46) -> 7 | C46: =COUNTIF('Best Bets'!I:I,A46) -> 0
A47: Total | B47: =SUM(B29:B46) -> 959 | C47: =SUM(C29:C46) -> 302
A49: By price tier
A50: Group | B50: Products | C50: Best Bets
A51: $100-249 | B51: =COUNTIF('All Products'!G:G,A51) -> 777 | C51: =COUNTIF('Best Bets'!G:G,A51) -> 239
A52: $250-499 | B52: =COUNTIF('All Products'!G:G,A52) -> 143 | C52: =COUNTIF('Best Bets'!G:G,A52) -> 50
A53: $500-999 | B53: =COUNTIF('All Products'!G:G,A53) -> 27 | C53: =COUNTIF('Best Bets'!G:G,A53) -> 10
A54: $1,000+ | B54: =COUNTIF('All Products'!G:G,A54) -> 12 | C54: =COUNTIF('Best Bets'!G:G,A54) -> 3
A55: Total | B55: =SUM(B51:B54) -> 959 | C55: =SUM(C51:C54) -> 302
